realsqltool/__init__.py
realsqltool/cli.py
realsqltool/connection.py
realsqltool/query.py
realsqltool/utils.py
realsqltool-0.1.1.dist-info/entry_points.txt
realsqltool-0.1.1.dist-info/licenses/LICENSE
realsqltool-0.1.1.dist-info/METADATA
realsqltool-0.1.1.dist-info/WHEEL
realsqltool-0.1.1.dist-info/RECORD
