Metadata-Version: 2.4
Name: realsqltool
Version: 0.1.1
Summary: A Python package for querying Azure SQL Server via ODBC
License-File: LICENSE
Author: Your Name
Author-email: you@example.com
Requires-Python: >=3.8
Classifier: Programming Language :: Python :: 3
Classifier: Programming Language :: Python :: 3.8
Classifier: Programming Language :: Python :: 3.9
Classifier: Programming Language :: Python :: 3.10
Classifier: Programming Language :: Python :: 3.11
Classifier: Programming Language :: Python :: 3.12
Classifier: Programming Language :: Python :: 3.13
Classifier: Programming Language :: Python :: 3.14
Requires-Dist: pandas (>=2.0.0)
Requires-Dist: pyodbc (>=5.0.0)
